<?xml version="1.0" encoding="utf-8"?>
<deegreeServicesMetadata xmlns="http://www.deegree.org/services/metadata" xmlns:xsi="http://www.w3.org/2001/XMLSchema-instance" configVersion="3.2.0" xsi:schemaLocation="http://www.deegree.org/services/metadata http://schemas.deegree.org/services/metadata/3.2.0/metadata.xsd">
	<ServiceIdentification>
		<Title>eENVplus Bio-geographical Regions WFS</Title>
		<Abstract>This is the eENVplus Bio-geographical Regions INSPIRE Download Service</Abstract>
		<Fees>NONE</Fees>
		<AccessConstraints>NONE</AccessConstraints>
	</ServiceIdentification>
	<ServiceProvider>
		<ProviderName>eENVplus Project</ProviderName>
		<ProviderSite>http://www.eenvplus.eu/</ProviderSite>
		<ServiceContact>
			<IndividualName>Alessio Giori</IndividualName>
			<PositionName>Analyst and Software developer</PositionName>
			<Phone>+390461283393</Phone>
			<Facsimile>+390461283398</Facsimile>
			<ElectronicMailAddress>info@eenvplus.eu</ElectronicMailAddress>
			<Address>
				<DeliveryPoint>Via alla Cascata, 56/C</DeliveryPoint>
				<City>Trento</City>
				<AdministrativeArea>tn</AdministrativeArea>
				<PostalCode>38123</PostalCode>
				<Country>Italy</Country>
			</Address>
			<OnlineResource>http://www.eenvplus.eu/</OnlineResource>
			<HoursOfService>8x5</HoursOfService>
			<ContactInstructions>Do not hesitate to call</ContactInstructions>
			<Role>PointOfContact</Role>
		</ServiceContact>
	</ServiceProvider>
	<!-- Extended Capabilities for INSPIRE Download Service -->
	<ExtendedCapabilities protocolVersions="2.0.0">
		<ows:ExtendedCapabilities xmlns:ows="http://www.opengis.net/ows/1.1">
			<!-- This special treatment (container element) for WFS 2.0.0 is required to provide schema-valid GetCapabilities responses. Can be removed once correct inspire_ds schemas for OWS commons 1.1.0/WFS 2.0.0 are available. -->
			<inspire_dls:ExtendedCapabilities xmlns:xsi="http://www.w3.org/2001/XMLSchema-instance" xmlns:inspire_dls="http://inspire.ec.europa.eu/schemas/inspire_dls/1.0" xmlns:inspire_common="http://inspire.ec.europa.eu/schemas/common/1.0" xsi:schemaLocation=" http://inspire.ec.europa.eu/schemas/common/1.0 http://inspire.ec.europa.eu/schemas/common/1.0/common.xsd http://inspire.ec.europa.eu/schemas/inspire_dls/1.0 http://inspire.ec.europa.eu/schemas/inspire_dls/1.0/inspire_dls.xsd">
				<inspire_common:ResourceLocator>
					<inspire_common:URL>http://eenvplus.sinergis.it/deegree/services/br?service=WFS&amp;request=GetCapabilities</inspire_common:URL>
				</inspire_common:ResourceLocator>
				<inspire_common:ResourceType>service</inspire_common:ResourceType>
				<inspire_common:TemporalReference/>
				<inspire_common:Conformity>
					<inspire_common:Specification>
						<inspire_common:Title>eENVplus Bio-geographical Regions WFS</inspire_common:Title>
						<inspire_common:DateOfPublication>2015-07-24</inspire_common:DateOfPublication>
					</inspire_common:Specification>
					<inspire_common:Degree>notEvaluated</inspire_common:Degree>
				</inspire_common:Conformity>
				<inspire_common:MetadataPointOfContact>
					<inspire_common:OrganisationName>Fondazione GraphiTech</inspire_common:OrganisationName>
					<inspire_common:EmailAddress>eenvplus@graphitech.it</inspire_common:EmailAddress>
				</inspire_common:MetadataPointOfContact>
				<inspire_common:MetadataDate>2015-07-24</inspire_common:MetadataDate>
				<inspire_common:SpatialDataServiceType>download</inspire_common:SpatialDataServiceType>
				<inspire_common:MandatoryKeyword>
					<inspire_common:KeywordValue>infoFeatureAccessService</inspire_common:KeywordValue>
				</inspire_common:MandatoryKeyword>
				<inspire_common:SupportedLanguages>
					<inspire_common:DefaultLanguage>
						<inspire_common:Language>eng</inspire_common:Language>
					</inspire_common:DefaultLanguage>
				</inspire_common:SupportedLanguages>
				<inspire_common:ResponseLanguage>
					<inspire_common:Language>eng</inspire_common:Language>
				</inspire_common:ResponseLanguage>
				<inspire_dls:SpatialDataSetIdentifier>
					<inspire_common:Code>br</inspire_common:Code>
					<inspire_common:Namespace>http://www.eenvplus.eu</inspire_common:Namespace>
				</inspire_dls:SpatialDataSetIdentifier>
			</inspire_dls:ExtendedCapabilities>
		</ows:ExtendedCapabilities>
	</ExtendedCapabilities>
</deegreeServicesMetadata>
