<?xml version="1.0" encoding="utf-8"?>
<deegreeWFS xmlns="http://www.deegree.org/services/wfs" xmlns:xsi="http://www.w3.org/2001/XMLSchema-instance" configVersion="3.2.0" xsi:schemaLocation="http://www.deegree.org/services/wfs http://schemas.deegree.org/services/wfs/3.2.0/wfs_configuration.xsd">
	<SupportedVersions>
    <Version>2.0.0</Version>
    <Version>1.1.0</Version>
	</SupportedVersions>
  
	<FeatureStoreId>inspire_pf</FeatureStoreId>
  
  <!-- WFS-T -->
  <EnableTransactions idGen="GenerateNew">false</EnableTransactions>
  
	<!-- The first CRS is the default one -->
	<QueryCRS>EPSG:3035</QueryCRS>
  
	<!-- Other CRSs -->
	<QueryCRS>EPSG:3034</QueryCRS>
	<QueryCRS>EPSG:3038</QueryCRS>
	<QueryCRS>EPSG:3039</QueryCRS>
	<QueryCRS>EPSG:3040</QueryCRS>
	<QueryCRS>EPSG:3041</QueryCRS>
	<QueryCRS>EPSG:3042</QueryCRS>
	<QueryCRS>EPSG:3043</QueryCRS>
	<QueryCRS>EPSG:3044</QueryCRS>
	<QueryCRS>EPSG:3045</QueryCRS>
	<QueryCRS>EPSG:3046</QueryCRS>
	<QueryCRS>EPSG:3047</QueryCRS>
	<QueryCRS>EPSG:3048</QueryCRS>
	<QueryCRS>EPSG:3049</QueryCRS>
	<QueryCRS>EPSG:3050</QueryCRS>
	<QueryCRS>EPSG:3051</QueryCRS>
	<QueryCRS>EPSG:4258</QueryCRS>
	<QueryCRS>EPSG:4936</QueryCRS>
	<QueryCRS>EPSG:4937</QueryCRS>
	<QueryCRS>EPSG:5730</QueryCRS>
	<QueryCRS>EPSG:7409</QueryCRS>
  
	<!-- Unlimited features -->
	<QueryMaxFeatures>-1</QueryMaxFeatures>
  
	<!-- Stored Queries are defined in an external file -->
	<StoredQuery>../storedqueries/inspireGetSpatialDatasetQuery.xml</StoredQuery>
  
  <!-- Configuration for the output GML format -->
	<GMLFormat gmlVersion="GML_32">
		<MimeType>text/xml; subtype=gml/3.2.1</MimeType>
		<MimeType>application/gml+xml; version=3.2</MimeType>
		<GetFeatureResponse xmlns:gml="http://www.opengis.net/gml/3.2">
			<DisableDynamicSchema>false</DisableDynamicSchema>
		</GetFeatureResponse>
	</GMLFormat>
</deegreeWFS>
